shell_command_logger/__init__.py
shell_command_logger/alias.py
shell_command_logger/backports.py
shell_command_logger/config.py
shell_command_logger/debug.py
shell_command_logger/default_aliases.txt
shell_command_logger/list_manager.py
shell_command_logger/main_file.py
shell_command_logger/output_dir_readme_template.md
shell_command_logger/pretty_exec.py
shell_command_logger/recorder.py
shell_command_logger/replay.py
shell_command_logger/search.py
shell_command_logger/symlink.py
shell_command_logger/cli/__init__.py
shell_command_logger/cli/alias.py
shell_command_logger/cli/check.py
shell_command_logger/cli/config.py
shell_command_logger/cli/log.py
shell_command_logger/cli/main.py
shell_command_logger/cli/replay.py
shell_command_logger/cli/search.py
shell_command_logger/cli/symlink.py
shell_command_logger/logger/__init__.py
shell_command_logger/logger/base_class.py
shell_command_logger/logger/python_logger.py
shell_command_logger/logger/script_linux.py
shell_command_logger/logger/script_macos.py
shell_command_logger-0.4.1.data/scripts/scl
shell_command_logger-0.4.1.data/scripts/scl-record-script
shell_command_logger-0.4.1.dist-info/LICENSE
shell_command_logger-0.4.1.dist-info/METADATA
shell_command_logger-0.4.1.dist-info/WHEEL
shell_command_logger-0.4.1.dist-info/top_level.txt
shell_command_logger-0.4.1.dist-info/RECORD
