Metadata-Version: 2.1
Name: shell-command-logger
Version: 0.4.1
Summary: Logs the output of commands, so that it can be replayed later
Home-page: https://github.com/six-two/shell-command-logger
Author: six-two
Author-email: pip@six-two.dev
License: MIT License
Classifier: License :: OSI Approved :: MIT License
Classifier: Operating System :: POSIX :: Linux
Classifier: Programming Language :: Python :: 3
Classifier: Programming Language :: Python :: 3.9
Classifier: Programming Language :: Python :: 3.10
Requires-Python: >=3.8
License-File: LICENSE
Provides-Extra: full
Requires-Dist: termcolor >=1.1.0 ; extra == 'full'
Requires-Dist: python-dateutil >=2.8.0 ; extra == 'full'
